plaetossdk/__init__.py
plaetossdk-1.0.2.dist-info/LICENSE
plaetossdk-1.0.2.dist-info/METADATA
plaetossdk-1.0.2.dist-info/WHEEL
plaetossdk-1.0.2.dist-info/top_level.txt
plaetossdk-1.0.2.dist-info/RECORD
