Metadata-Version: 2.1
Name: plaetossdk
Version: 1.0.2
Summary: SDK for Plaetos ML services.
Home-page: https://github.com/csight/plaetossdk
Author: Mark Moloney
Author-email: markm@plaetos.com
Project-URL: Bug Tracker, https://github.com/csight/plaetossdk/issues
Classifier: Programming Language :: Python :: 3
Classifier: License :: OSI Approved :: MIT License
Classifier: Operating System :: OS Independent
Requires-Python: >=3.6
License-File: LICENSE
